setup.py
test/__init__.py
test/test_access_path.py
test/test_access_path_create_req.py
test/test_access_path_create_req_access_path.py
test/test_access_path_nestview.py
test/test_access_path_resp.py
test/test_access_path_update_req.py
test/test_access_path_update_req_access_path.py
test/test_access_paths_api.py
test/test_access_paths_resp.py
test/test_access_token.py
test/test_access_token_create_record.py
test/test_access_token_create_req.py
test/test_access_token_create_req_access_token.py
test/test_access_token_create_resp.py
test/test_access_token_resp.py
test/test_access_tokens_api.py
test/test_access_tokens_resp.py
test/test_action_log.py
test/test_action_logs_api.py
test/test_action_logs_resp.py
test/test_alert.py
test/test_alert_action_req.py
test/test_alert_action_req_alert.py
test/test_alert_group.py
test/test_alert_group_create_req.py
test/test_alert_group_create_req_alert_group.py
test/test_alert_group_resp.py
test/test_alert_group_update_req.py
test/test_alert_group_update_req_alert_group.py
test/test_alert_groups_api.py
test/test_alert_groups_resp.py
test/test_alert_resp.py
test/test_alert_rule.py
test/test_alert_rule_create_req.py
test/test_alert_rule_create_req_rule.py
test/test_alert_rule_resp.py
test/test_alert_rule_schema.py
test/test_alert_rule_schema_resp.py
test/test_alert_rule_update_req.py
test/test_alert_rule_update_req_rule.py
test/test_alert_rules_api.py
test/test_alert_rules_resp.py
test/test_alert_stats.py
test/test_alert_stats_resp.py
test/test_alerts_action_req.py
test/test_alerts_action_req_alerts.py
test/test_alerts_api.py
test/test_alerts_resp.py
test/test_auth_api.py
test/test_auth_login_req.py
test/test_auth_login_req_auth.py
test/test_auth_password_req.py
test/test_auth_password_req_user.py
test/test_auth_token_req.py
test/test_block_replication_config.py
test/test_block_snapshots_api.py
test/test_block_volume_group_snapshots_api.py
test/test_block_volume_groups_api.py
test/test_block_volumes_api.py
test/test_boot_node.py
xms_client.egg-info/PKG-INFO
xms_client.egg-info/SOURCES.txt
xms_client.egg-info/dependency_links.txt
xms_client.egg-info/requires.txt
xms_client.egg-info/top_level.txt
