Metadata-Version: 1.0
Name: xms-client
Version: 3.2.14
Summary: XMS API
Home-page: http://github.xsky.com/Tiger/XSKY-XMS-BASIS
Author: xsky
Author-email: haihao@xsky.com
License: UNKNOWN
Keywords: Swagger,XMS API,XSky
Platform: UNKNOWN
